picnik.py
picnik-1.1.1.dist-info/LICENSE
picnik-1.1.1.dist-info/WHEEL
picnik-1.1.1.dist-info/METADATA
picnik-1.1.1.dist-info/RECORD
