Metadata-Version: 2.1
Name: picnik
Version: 1.1.1
Summary: A package to make isoconversional computations for non-isothermal kinetics
Home-page: https://github.com/ErickErock/pICNIK
License: MIT
Keywords: non-isothermal kinetics,isoconversion,isoconversional computations,model-free predictions
Author: ErickErock
Author-email: ramirez.orozco.erick@gmail.com
Requires-Python: >=3.7,<4.0
Classifier: License :: OSI Approved :: MIT License
Classifier: Programming Language :: Python :: 3
Classifier: Programming Language :: Python :: 3.10
Classifier: Programming Language :: Python :: 3.7
Classifier: Programming Language :: Python :: 3.8
Classifier: Programming Language :: Python :: 3.9
Requires-Dist: matplotlib (>=3.10.0,<4.0.0)
Requires-Dist: numpy (>=2.0.0,<3.0.0)
Requires-Dist: pandas (>=2.2.0,<3.0.0)
Requires-Dist: picnik_integrator
Requires-Dist: rxnmodel
Requires-Dist: scipy (>=1.15.3,<2.0.0)
Project-URL: Repository, https://github.com/ErickErock/pICNIK
